tiktok_ads_mcp/__init__.py
tiktok_ads_mcp/oauth_simple.py
tiktok_ads_mcp/server.py
tiktok_ads_mcp/tiktok_client.py
tiktok_ads_mcp/tools/__init__.py
tiktok_ads_mcp/tools/audience_tools.py
tiktok_ads_mcp/tools/campaign_tools.py
tiktok_ads_mcp/tools/creative_tools.py
tiktok_ads_mcp/tools/performance_tools.py
tiktok_ads_mcp/tools/reporting_tools.py
iflow_mcp_adsmcp_tiktok_ads_mcp-0.1.3.dist-info/METADATA
iflow_mcp_adsmcp_tiktok_ads_mcp-0.1.3.dist-info/WHEEL
iflow_mcp_adsmcp_tiktok_ads_mcp-0.1.3.dist-info/entry_points.txt
iflow_mcp_adsmcp_tiktok_ads_mcp-0.1.3.dist-info/licenses/LICENSE
iflow_mcp_adsmcp_tiktok_ads_mcp-0.1.3.dist-info/RECORD
