Metadata-Version: 2.4
Name: iflow-mcp_adsmcp_tiktok-ads-mcp
Version: 0.1.3
Summary: Model Context Protocol server for TikTok Ads API integration
Project-URL: Homepage, https://github.com/adsmcp/tiktok-ads-mcp
Project-URL: Repository, https://github.com/adsmcp/tiktok-ads-mcp
Project-URL: Documentation, https://docs.adsmcp.com/tiktok
Author-email: AdsMCP Team <support@adsmcp.com>
License: MIT
License-File: LICENSE
Classifier: Development Status :: 3 - Alpha
Classifier: Intended Audience :: Developers
Classifier: License :: OSI Approved :: MIT License
Classifier: Programming Language :: Python :: 3
Classifier: Programming Language :: Python :: 3.10
Classifier: Programming Language :: Python :: 3.11
Classifier: Programming Language :: Python :: 3.12
Requires-Python: >=3.10
Requires-Dist: aiohttp>=3.12.15
Requires-Dist: asyncio>=3.4.3
Requires-Dist: httpx>=0.25.0
Requires-Dist: mcp>=1.0.0
Requires-Dist: pydantic>=2.0.0
Requires-Dist: python-dotenv>=1.0.0
Requires-Dist: six>=1.16.0
Requires-Dist: typing-extensions>=4.0.0
Provides-Extra: dev
Requires-Dist: black>=23.0.0; extra == 'dev'
Requires-Dist: flake8>=6.0.0; extra == 'dev'
Requires-Dist: isort>=5.12.0; extra == 'dev'
Requires-Dist: mypy>=1.0.0; extra == 'dev'
Requires-Dist: pytest-asyncio>=0.21.0; extra == 'dev'
Requires-Dist: pytest>=7.0.0; extra == 'dev'
